robustbench/__init__.py
robustbench/data.py
robustbench/eval.py
robustbench/loaders.py
robustbench/utils.py
robustbench/zenodo_download.py
robustbench/helper_files/imagenet_class_to_id_map.json
robustbench/helper_files/imagenet_test_image_ids.txt
robustbench/leaderboard/__init__.py
robustbench/leaderboard/template.py
robustbench/model_zoo/__init__.py
robustbench/model_zoo/cifar10.py
robustbench/model_zoo/cifar100.py
robustbench/model_zoo/enums.py
robustbench/model_zoo/imagenet.py
robustbench/model_zoo/models.py
robustbench/model_zoo/architectures/CARD_resnet.py
robustbench/model_zoo/architectures/MIMIR_swin_transformer.py
robustbench/model_zoo/architectures/Meansparse_ra_wrn_70_16.py
robustbench/model_zoo/architectures/Meansparse_swin_L.py
robustbench/model_zoo/architectures/Meansparse_wrn_70_16.py
robustbench/model_zoo/architectures/Meansparse_wrn_94_16.py
robustbench/model_zoo/architectures/__init__.py
robustbench/model_zoo/architectures/alexnet.py
robustbench/model_zoo/architectures/bit_rn.py
robustbench/model_zoo/architectures/bit_rn_v2.py
robustbench/model_zoo/architectures/boosting_wide_resnet.py
robustbench/model_zoo/architectures/comp_model.py
robustbench/model_zoo/architectures/convnext_v2.py
robustbench/model_zoo/architectures/convstem_models.py
robustbench/model_zoo/architectures/deit.py
robustbench/model_zoo/architectures/dm_rn.py
robustbench/model_zoo/architectures/dm_wide_resnet.py
robustbench/model_zoo/architectures/mixing_net.py
robustbench/model_zoo/architectures/optimal_spca.yaml
robustbench/model_zoo/architectures/output_maps.py
robustbench/model_zoo/architectures/paf_wide_resnet.py
robustbench/model_zoo/architectures/resnest.py
robustbench/model_zoo/architectures/resnet.py
robustbench/model_zoo/architectures/resnext.py
robustbench/model_zoo/architectures/robust_resnet.py
robustbench/model_zoo/architectures/robust_wide_resnet.py
robustbench/model_zoo/architectures/robustarch_wide_resnet.py
robustbench/model_zoo/architectures/sodef_layers.py
robustbench-1.1.1.dist-info/LICENSE
robustbench-1.1.1.dist-info/METADATA
robustbench-1.1.1.dist-info/WHEEL
robustbench-1.1.1.dist-info/top_level.txt
robustbench-1.1.1.dist-info/RECORD
