Metadata-Version: 2.1
Name: robustbench
Version: 1.1.1
Summary: This package provides the data for RobustBench together with the model zoo.
Home-page: https://github.com/RobustBench/robustbench
Author: Francesco Croce, Maksym Andriushchenko, Vikash Sehwag, Edoardo Debenedetti
Author-email: adversarial.benchmark@gmail.com
Classifier: Programming Language :: Python :: 3
Classifier: License :: OSI Approved :: Apache Software License
Classifier: Operating System :: OS Independent
License-File: LICENSE
Requires-Dist: torch >=1.7.1
Requires-Dist: torchvision >=0.8.2
Requires-Dist: torchdiffeq
Requires-Dist: geotorch
Requires-Dist: requests >=2.25.0
Requires-Dist: numpy >=1.19.4
Requires-Dist: Jinja2 ~=3.1.2
Requires-Dist: tqdm >=4.56.1
Requires-Dist: pandas >=1.3.5
Requires-Dist: pyautoattack >=0.2.0
Requires-Dist: timm ==1.0.9
Requires-Dist: gdown ==5.1.0
Requires-Dist: pyyaml
